AUTHORS.rst
LICENSE
README.rst
setup.cfg
setup.py
oreille/__init__.py
oreille/export.py
oreille/oreille.py
oreille.egg-info/PKG-INFO
oreille.egg-info/SOURCES.txt
oreille.egg-info/dependency_links.txt
oreille.egg-info/not-zip-safe
oreille.egg-info/requires.txt
oreille.egg-info/top_level.txt
tests/test_export.py
tests/test_oreille.py